README.rst
setup.py
pegaxml/__init__.py
pegaxml/pegadados.py
pegaxml.egg-info/PKG-INFO
pegaxml.egg-info/SOURCES.txt
pegaxml.egg-info/dependency_links.txt
pegaxml.egg-info/not-zip-safe
pegaxml.egg-info/requires.txt
pegaxml.egg-info/top_level.txt